AUTHORS
tof/__init__.py
tof/admin.py
tof/apps.py
tof/decorators.py
tof/fields.py
tof/fixtures/languages_data.json.gz
tof/forms.py
tof/management/__init__.py
tof/management/commands/benchmark.py
tof/managers.py
tof/migrations/0001_initial.py
tof/migrations/0002_auto_20191118_1000.py
tof/migrations/0003_auto_20191127_0907.py
tof/migrations/__init__.py
tof/models.py
tof/settings.py
tof/static/tof/css/style.css
tof/static/tof/js/translatable_fields_form.js
tof/static/tof/js/translatable_fields_widget.js
tof/static/tof/js/translation_form.js
tof/static/tof/js/translation_inline.js
tof/templates/tof/multiwidget.html
tof/tests/__init__.py
tof/tests/tests.py
tof/utils.py
tof/views.py
django_tof-0.3.1.dist-info/LICENSE
django_tof-0.3.1.dist-info/WHEEL
django_tof-0.3.1.dist-info/METADATA
django_tof-0.3.1.dist-info/RECORD
