Metadata-Version: 2.1
Name: django-tof
Version: 0.3.1
Summary: Translate fields of django models without having to restart the server,  without changing the model code.
Home-page: https://github.com/mom1/django-tof/wiki/django-tof
License: MIT
Keywords: translations,translate,django,model
Author: MaxST
Author-email: mstolpasov@gmail.com
Requires-Python: >=3.6,<4.0
Classifier: Development Status :: 5 - Production/Stable
Classifier: Environment :: Web Environment
Classifier: Framework :: Django
Classifier: Intended Audience :: Developers
Classifier: License :: OSI Approved :: MIT License
Classifier: Operating System :: OS Independent
Classifier: Programming Language :: Python
Classifier: Programming Language :: Python :: 3
Classifier: Programming Language :: Python :: 3.6
Classifier: Programming Language :: Python :: 3.7
Classifier: Programming Language :: Python :: 3.8
Classifier: Topic :: Database
Classifier: Topic :: Internet :: WWW/HTTP :: Dynamic Content
Classifier: Topic :: Text Processing :: Linguistic
Requires-Dist: django (>=2.2)
Project-URL: Repository, https://github.com/mom1/django-tof
